autogluon.cloud-0.4.2-py3.8-nspkg.pth
autogluon/cloud/__init__.py
autogluon/cloud/version.py
autogluon/cloud/backend/__init__.py
autogluon/cloud/backend/backend.py
autogluon/cloud/backend/backend_factory.py
autogluon/cloud/backend/constant.py
autogluon/cloud/backend/multimodal_sagemaker_backend.py
autogluon/cloud/backend/ray_aws_backend.py
autogluon/cloud/backend/ray_backend.py
autogluon/cloud/backend/sagemaker_backend.py
autogluon/cloud/backend/tabular_sagemaker_backend.py
autogluon/cloud/backend/timeseries_sagemaker_backend.py
autogluon/cloud/cluster/__init__.py
autogluon/cloud/cluster/cluster_config_generator.py
autogluon/cloud/cluster/cluster_manager.py
autogluon/cloud/cluster/constants.py
autogluon/cloud/cluster/ray_aws_cluster_config_generator.py
autogluon/cloud/cluster/ray_aws_cluster_manager.py
autogluon/cloud/cluster/ray_cluster_config_generator.py
autogluon/cloud/cluster/ray_cluster_manager.py
autogluon/cloud/data/__init__.py
autogluon/cloud/data/format_converter.py
autogluon/cloud/default_cluster_configs/__init__.py
autogluon/cloud/default_cluster_configs/ray_aws_default_cluster_config.yaml
autogluon/cloud/endpoint/__init__.py
autogluon/cloud/endpoint/endpoint.py
autogluon/cloud/endpoint/sagemaker_endpoint.py
autogluon/cloud/job/__init__.py
autogluon/cloud/job/ray_job.py
autogluon/cloud/job/remote_job.py
autogluon/cloud/job/sagemaker_job.py
autogluon/cloud/predictor/__init__.py
autogluon/cloud/predictor/cloud_predictor.py
autogluon/cloud/predictor/multimodal_cloud_predictor.py
autogluon/cloud/predictor/tabular_cloud_predictor.py
autogluon/cloud/predictor/timeseries_cloud_predictor.py
autogluon/cloud/scripts/__init__.py
autogluon/cloud/scripts/script_manager.py
autogluon/cloud/scripts/ray_scripts/__init__.py
autogluon/cloud/scripts/ray_scripts/train.py
autogluon/cloud/scripts/sagemaker_scripts/__init__.py
autogluon/cloud/scripts/sagemaker_scripts/multimodal_serve.py
autogluon/cloud/scripts/sagemaker_scripts/tabular_serve.py
autogluon.cloud-0.4.2.dist-info/LICENSE
autogluon.cloud-0.4.2.dist-info/METADATA
autogluon.cloud-0.4.2.dist-info/NOTICE
autogluon.cloud-0.4.2.dist-info/WHEEL
autogluon.cloud-0.4.2.dist-info/namespace_packages.txt
autogluon.cloud-0.4.2.dist-info/top_level.txt
autogluon.cloud-0.4.2.dist-info/zip-safe
autogluon.cloud-0.4.2.dist-info/RECORD
