Metadata-Version: 2.1
Name: autogluon.cloud
Version: 0.4.2
Summary: Train and deploy AutoGluon backed models on the cloud
Home-page: https://github.com/autogluon/autogluon-cloud
Author: AutoGluon Community
License: Apache-2.0
Project-URL: Documentation, https://auto.gluon.ai
Project-URL: Bug Reports, https://github.com/autogluon/autogluon-cloud/issues
Project-URL: Source, https://github.com/autogluon/autogluon-cloud/
Project-URL: Contribute!, https://github.com/autogluon/autogluon-cloud/blob/master/CONTRIBUTING.md
Platform: UNKNOWN
Classifier: Development Status :: 4 - Beta
Classifier: Intended Audience :: Education
Classifier: Intended Audience :: Developers
Classifier: Intended Audience :: Science/Research
Classifier: Intended Audience :: Customer Service
Classifier: Intended Audience :: Financial and Insurance Industry
Classifier: Intended Audience :: Healthcare Industry
Classifier: Intended Audience :: Telecommunications Industry
Classifier: License :: OSI Approved :: Apache Software License
Classifier: Operating System :: MacOS
Classifier: Operating System :: Microsoft :: Windows
Classifier: Operating System :: POSIX
Classifier: Operating System :: Unix
Classifier: Programming Language :: Python :: 3
Classifier: Programming Language :: Python :: 3.8
Classifier: Programming Language :: Python :: 3.9
Classifier: Programming Language :: Python :: 3.10
Classifier: Programming Language :: Python :: 3.11
Classifier: Topic :: Software Development
Classifier: Topic :: Scientific/Engineering :: Artificial Intelligence
Classifier: Topic :: Scientific/Engineering :: Information Analysis
Classifier: Topic :: Scientific/Engineering :: Image Recognition
Requires-Python: >=3.8, <3.12
Requires-Dist: autogluon.common>=0.7
Requires-Dist: boto3<2.0,>=1.10
Requires-Dist: packaging<25.0,>=23.0
Requires-Dist: sagemaker<3.0,>=2.126.0
Requires-Dist: pyarrow<11.1,>=11.0
Requires-Dist: PyYAML~=6.0
Requires-Dist: Pillow<11,>=10.2
Requires-Dist: ray[default]<2.11,>=2.10.0
Provides-Extra: all
Requires-Dist: autogluon>=0.7; extra == "all"
Provides-Extra: tests
Requires-Dist: pytest; extra == "tests"
Requires-Dist: tox; extra == "tests"
Requires-Dist: autogluon.common>=0.7; extra == "tests"
Requires-Dist: pytest-cov; extra == "tests"
Requires-Dist: moto; extra == "tests"
